RsCma/RsCma.py
RsCma/__init__.py
RsCma/enums.py
RsCma/repcap.py
RsCma/CustomFiles/__init__.py
RsCma/CustomFiles/events.py
RsCma/CustomFiles/reliability.py
RsCma/CustomFiles/utilities.py
RsCma/Implementations/FirmwareUpdate.py
RsCma/Implementations/RecallState.py
RsCma/Implementations/SaveState.py
RsCma/Implementations/Unit.py
RsCma/Implementations/__init__.py
RsCma/Implementations/AfRf/__init__.py
RsCma/Implementations/AfRf/Measurement/__init__.py
RsCma/Implementations/AfRf/Measurement/Digital/__init__.py
RsCma/Implementations/AfRf/Measurement/Digital/Dmr/Sinfo.py
RsCma/Implementations/AfRf/Measurement/Digital/Dmr/__init__.py
RsCma/Implementations/AfRf/Measurement/Digital/Dmr/BitErrorRate/Current.py
RsCma/Implementations/AfRf/Measurement/Digital/Dmr/BitErrorRate/Maximum.py
RsCma/Implementations/AfRf/Measurement/Digital/Dmr/BitErrorRate/__init__.py
RsCma/Implementations/AfRf/Measurement/Digital/Dmr/PoOff/Current.py
RsCma/Implementations/AfRf/Measurement/Digital/Dmr/PoOff/__init__.py
RsCma/Implementations/AfRf/Measurement/Digital/Dmr/Power/Current.py
RsCma/Implementations/AfRf/Measurement/Digital/Dmr/Power/__init__.py
RsCma/Implementations/AfRf/Measurement/Digital/PtFive/Sinfo.py
RsCma/Implementations/AfRf/Measurement/Digital/PtFive/__init__.py
RsCma/Implementations/AfRf/Measurement/Digital/PtFive/BitErrorRate/Current.py
RsCma/Implementations/AfRf/Measurement/Digital/PtFive/BitErrorRate/Maximum.py
RsCma/Implementations/AfRf/Measurement/Digital/PtFive/BitErrorRate/__init__.py
RsCma/Implementations/AfRf/Measurement/Digital/PtFive/Power/Current.py
RsCma/Implementations/AfRf/Measurement/Digital/PtFive/Power/__init__.py
RsCma/Implementations/AfRf/Measurement/Digital/State/All.py
RsCma/Implementations/AfRf/Measurement/Digital/State/__init__.py
RsCma/Implementations/AfRf/Measurement/Digital/Tetra/Sinfo.py
RsCma/Implementations/AfRf/Measurement/Digital/Tetra/__init__.py
RsCma/Implementations/AfRf/Measurement/Digital/Tetra/BitErrorRate/Current.py
rscma-4.0.22.dist-info/METADATA
rscma-4.0.22.dist-info/WHEEL
rscma-4.0.22.dist-info/top_level.txt
rscma-4.0.22.dist-info/RECORD
